enn/__init__.py
enn/benchmarks/__init__.py
enn/benchmarks/ackley.py
enn/benchmarks/ackley_class.py
enn/benchmarks/ackley_core.py
enn/benchmarks/double_ackley.py
enn/enn/candidates.py
enn/enn/conditional_posterior_draw_internals.py
enn/enn/draw_internals.py
enn/enn/enn.py
enn/enn/enn_class.py
enn/enn/enn_conditional.py
enn/enn/enn_fit.py
enn/enn/enn_hash.py
enn/enn/enn_index.py
enn/enn/enn_like_protocol.py
enn/enn/enn_normal.py
enn/enn/enn_params.py
enn/enn/enn_params_class.py
enn/enn/enn_util.py
enn/enn/neighbor_data.py
enn/enn/neighbors.py
enn/enn/posterior_flags.py
enn/enn/weighted_stats.py
enn/turbo/hypervolume.py
enn/turbo/impl_helpers.py
enn/turbo/morbo_trust_region.py
enn/turbo/no_trust_region.py
enn/turbo/optimizer.py
enn/turbo/optimizer_config.py
enn/turbo/proposal.py
enn/turbo/sampling.py
enn/turbo/turbo_gp.py
enn/turbo/turbo_gp_base.py
enn/turbo/turbo_gp_fit.py
enn/turbo/turbo_gp_noisy.py
enn/turbo/turbo_optimizer_utils.py
enn/turbo/turbo_trust_region.py
enn/turbo/turbo_utils.py
enn/turbo/components/__init__.py
enn/turbo/components/acquisition.py
enn/turbo/components/builder.py
enn/turbo/components/chebyshev_incumbent_selector.py
enn/turbo/components/enn_surrogate.py
enn/turbo/components/gp_surrogate.py
enn/turbo/components/hnr_acq_optimizer.py
enn/turbo/components/incumbent_selector.py
enn/turbo/components/incumbent_selector_protocol.py
enn/turbo/components/no_incumbent_selector.py
enn/turbo/components/no_surrogate.py
enn/turbo/components/pareto_acq_optimizer.py
enn/turbo/components/posterior_result.py
enn/turbo/components/protocols.py
enn/turbo/components/random_acq_optimizer.py
enn/turbo/components/scalar_incumbent_selector.py
enn/turbo/components/surrogate_result.py
enn/turbo/components/surrogates.py
enn/turbo/components/thompson_acq_optimizer.py
enn/turbo/components/ucb_acq_optimizer.py
enn/turbo/config/__init__.py
enn/turbo/config/acq_type.py
enn/turbo/config/acquisition.py
enn/turbo/config/base.py
enn/turbo/config/candidate_gen_config.py
ennbo-0.1.9.dist-info/METADATA
ennbo-0.1.9.dist-info/WHEEL
ennbo-0.1.9.dist-info/licenses/LICENSE
ennbo-0.1.9.dist-info/RECORD
