Metadata-Version: 2.4
Name: ennbo
Version: 0.1.9
Summary: Epistemic Nearest Neighbors
Project-URL: Homepage, https://github.com/yubo-research/enn
Project-URL: Source, https://github.com/yubo-research/enn
Author-email: YUBO Lab <david.sweet@yu.edu>
License: MIT License
License-File: LICENSE
Classifier: Intended Audience :: Science/Research
Classifier: License :: OSI Approved :: MIT License
Classifier: Programming Language :: Python :: 3
Classifier: Programming Language :: Python :: 3.11
Classifier: Programming Language :: Python :: 3.12
Classifier: Topic :: Scientific/Engineering
Classifier: Topic :: Scientific/Engineering :: Artificial Intelligence
Classifier: Topic :: Scientific/Engineering :: Mathematics
Requires-Python: >=3.11
Requires-Dist: faiss-cpu>=1.9.0
Requires-Dist: gpytorch>=1.13
Requires-Dist: numpy<2.0.0,>=1.26.4
Requires-Dist: scipy>=1.15.3
Requires-Dist: torch>=2.5.1
Provides-Extra: dev
Requires-Dist: nbmake>=1.5; extra == 'dev'
Requires-Dist: pytest>=8.0; extra == 'dev'
Requires-Dist: ruff>=0.4; extra == 'dev'
